Week 5/pc.v
// Week 2 — Program Counter (6-bit)
// Priority: rst > load > inc > hold
// Run: iverilog -o sim ../testbenches/tb_pc.v pc.v && vvp sim

module pc(
    input            clk, rst, inc, load,
    input      [5:0] load_val,
    output reg [5:0] pc_out
);
    always @(posedge clk) begin
        // YOUR CODE HERE
        // if rst:  pc_out = 0
        // if load: pc_out = load_val
        // if inc:  pc_out = pc_out + 1
		  if(rst)
				pc_out <= 6'b000000;
			else if( load)
				pc_out <=load_val;
			else if(inc)
				pc_out <= pc_out+6'b000001;
    end
endmodule

Week 2/Assignment_done/tb_pc.v
module tb_pc;
    reg clk, rst, inc, load;
    reg [5:0] load_val;
    wire [5:0] pc_out;
    integer fail = 0;

    pc uut(.clk(clk),.rst(rst),.inc(inc),.load(load),.load_val(load_val),.pc_out(pc_out));

    always #5 clk = ~clk;

    initial begin
        $dumpfile("wave_pc.vcd"); $dumpvars(0,tb_pc);
        clk=0; rst=1; inc=0; load=0; load_val=0; #12;
        if(pc_out!==0) begin $display("FAIL: PC should be 0 after reset, got %0d", pc_out); fail=fail+1; end

        rst=0; inc=1; #10;
        if(pc_out!==1) begin $display("FAIL: PC should be 1 after inc, got %0d", pc_out); fail=fail+1; end
        #10;
        if(pc_out!==2) begin $display("FAIL: PC should be 2, got %0d", pc_out); fail=fail+1; end

        // Load a value
        inc=0; load=1; load_val=6'd20; #10;
        if(pc_out!==20) begin $display("FAIL: PC should be 20 after load, got %0d", pc_out); fail=fail+1; end

        // Increment from 20
        load=0; inc=1; #10;
        if(pc_out!==21) begin $display("FAIL: PC should be 21, got %0d", pc_out); fail=fail+1; end

        // Reset takes priority over inc
        rst=1; #10;
        if(pc_out!==0) begin $display("FAIL: rst should override inc, got %0d", pc_out); fail=fail+1; end

        if(fail==0) $display("PASS — all PC checks passed.");
        else        $display("FAIL — %0d check(s) failed.", fail);
        $finish;
    end
endmodule

Week 2/Assignment_done/wave_pc.vcd
$date
	Sat May 30 15:03:37 2026
$end
$version
	Icarus Verilog
$end
$timescale
	1s
$end
$scope module tb_pc $end
$var wire 6 ! pc_out [5:0] $end
$var reg 1 " clk $end
$var reg 1 # inc $end
$var reg 1 $ load $end
$var reg 6 % load_val [5:0] $end
$var reg 1 & rst $end
$var integer 32 ' fail [31:0] $end
$scope module uut $end
$var wire 1 " clk $end
$var wire 1 # inc $end
$var wire 1 $ load $end
$var wire 6 ( load_val [5:0] $end
$var wire 1 & rst $end
$var reg 6 ) pc_out [5:0] $end
$upscope $end
$upscope $end
$enddefinitions $end
$comment Show the parameter values. $end
$dumpall
$end
#0
$dumpvars
bx )
b0 (
b0 '
1&
b0 %
0$
0#
0"
bx !
$end
#5
b0 !
b0 )
1"
#10
0"
#12
1#
0&
#15
b1 !
b1 )
1"
#20
0"
#25
b10 !
b10 )
1"
#30
0"
#32
b10100 %
b10100 (
1$
0#
#35
b10100 !
b10100 )
1"
#40
0"
#42
1#
0$
#45
b10101 !
b10101 )
1"
#50
0"
#52
1&
#55
b0 !
b0 )
1"
